foray/__init__.py
foray/foray.cpython-313-x86_64-linux-gnu.so
foray-0.2.0.dist-info/METADATA
foray-0.2.0.dist-info/WHEEL
foray-0.2.0.dist-info/RECORD
