Metadata-Version: 2.4
Name: foray
Version: 0.2.0
Summary: An interactive and visualize signal processeing toolkit
Project-URL: Homepage, https://github.com/uw-mrtud/foray
Project-URL: Issues, https://github.com/uw-mrtud/foray/issues
Author-email: John Christensen <jechristens3@wisc.edu>
License-Expression: MIT
Classifier: Operating System :: OS Independent
Classifier: Programming Language :: Python :: 3
Requires-Python: >=3.12
